easyconfig/__const__.py
easyconfig/__init__.py
easyconfig/__version__.py
easyconfig/create_app_config.py
easyconfig/py.typed
easyconfig/config_objs/__init__.py
easyconfig/config_objs/app_config.py
easyconfig/config_objs/object_config.py
easyconfig/config_objs/subscription.py
easyconfig/errors/__init__.py
easyconfig/errors/errors.py
easyconfig/errors/handler.py
easyconfig/expansion/__init__.py
easyconfig/expansion/expand.py
easyconfig/expansion/load_file.py
easyconfig/expansion/load_var.py
easyconfig/expansion/location.py
easyconfig/models/__init__.py
easyconfig/models/app.py
easyconfig/models/config.py
easyconfig/models/convenience.py
easyconfig/models/field.py
easyconfig/pre_process/__init__.py
easyconfig/pre_process/base.py
easyconfig/pre_process/delete_entry.py
easyconfig/pre_process/move_entry.py
easyconfig/pre_process/pre_process.py
easyconfig/pre_process/rename_entry.py
easyconfig/yaml/__init__.py
easyconfig/yaml/align.py
easyconfig/yaml/from_model.py
easyconfig/yaml/yaml.py
easyconfig-0.4.2.dist-info/licenses/LICENSE
easyconfig-0.4.2.dist-info/METADATA
easyconfig-0.4.2.dist-info/WHEEL
easyconfig-0.4.2.dist-info/top_level.txt
easyconfig-0.4.2.dist-info/RECORD
