Metadata-Version: 2.4
Name: easyconfig
Version: 0.4.2
Summary: Easy application configuration with yaml files
Home-page: https://github.com/spacemanspiff2007/easyconfig
Author: spaceman_spiff
Project-URL: GitHub, https://github.com/spacemanspiff2007/easyconfig
Keywords: yaml,configuration,pydantic,settings,config,yml
Classifier: Development Status :: 4 - Beta
Classifier: Intended Audience :: Developers
Classifier: License :: OSI Approved :: Apache Software License
Classifier: Natural Language :: English
Classifier: Operating System :: OS Independent
Classifier: Programming Language :: Python :: 3.10
Classifier: Programming Language :: Python :: 3.11
Classifier: Programming Language :: Python :: 3.12
Classifier: Programming Language :: Python :: 3.13
Classifier: Programming Language :: Python :: 3.14
Classifier: Programming Language :: Python :: 3 :: Only
Classifier: Topic :: Software Development :: Libraries
Requires-Python: >=3.10
License-File: LICENSE
Requires-Dist: pydantic<3.0,>=2.0
Requires-Dist: pydantic-settings<3.0,>=2.0
Requires-Dist: ruamel.yaml<0.19,>=0.18
Requires-Dist: typing-extensions<5,>=4.4
Dynamic: author
Dynamic: classifier
Dynamic: description
Dynamic: description-content-type
Dynamic: home-page
Dynamic: keywords
Dynamic: license-file
Dynamic: project-url
Dynamic: requires-dist
Dynamic: requires-python
Dynamic: summary
